{
  "relationships": [
    {
      "relationshipId": 1,
      "relationshipType": "many-to-one",
      "relationshipName": "season",
      "otherEntityName": "season",
      "otherEntityField": "id"
    },
    {
      "relationshipId": 2,
      "relationshipType": "many-to-one",
      "relationshipName": "division",
      "otherEntityName": "division",
      "otherEntityField": "id"
    },
    {
      "relationshipId": 3,
      "relationshipType": "one-to-many",
      "relationshipName": "team",
      "otherEntityName": "team",
      "otherEntityRelationshipName": "divisionEvent"
    }
  ],
  "fields": [],
  "changelogDate": "20160914031740",
  "dto": "no",
  "pagination": "no",
  "service": "no",
  "entityTableName": "division_event"
}